{
  "date": "2026-02-09",
  "repo": "tile-ai/tilelang-ascend",
  "runs": [
    {
      "id": 21821807010,
      "name": "documentation",
      "head_branch": "npuir-parallel",
      "head_sha": "a289dada611b9d5226ac202ec01d63bec216eb13",
      "status": "completed",
      "conclusion": "startup_failure",
      "event": "pull_request_target",
      "created_at": "2026-02-09T10:40:57Z",
      "updated_at": "2026-02-09T10:40:57Z",
      "html_url": "https://github.com/tile-ai/tilelang-ascend/actions/runs/21821807010",
      "durationInSeconds": 0,
      "pull_requests": [],
      "jobs": []
    },
    {
      "id": 21821731723,
      "name": "CI",
      "head_branch": "npuir-parallel",
      "head_sha": "a289dada611b9d5226ac202ec01d63bec216eb13",
      "status": "completed",
      "conclusion": "startup_failure",
      "event": "pull_request",
      "created_at": "2026-02-09T10:38:26Z",
      "updated_at": "2026-02-09T10:38:26Z",
      "html_url": "https://github.com/tile-ai/tilelang-ascend/actions/runs/21821731723",
      "durationInSeconds": 0,
      "pull_requests": [],
      "jobs": []
    },
    {
      "id": 21821731307,
      "name": "Reminder Bot",
      "head_branch": "npuir-parallel",
      "head_sha": "a289dada611b9d5226ac202ec01d63bec216eb13",
      "status": "completed",
      "conclusion": "startup_failure",
      "event": "pull_request_target",
      "created_at": "2026-02-09T10:38:25Z",
      "updated_at": "2026-02-09T10:38:25Z",
      "html_url": "https://github.com/tile-ai/tilelang-ascend/actions/runs/21821731307",
      "durationInSeconds": 0,
      "pull_requests": [],
      "jobs": []
    },
    {
      "id": 21818352198,
      "name": "CI",
      "head_branch": "npuir-exp",
      "head_sha": "5635898c5cb5eaf373f583010ad940a8893ddb54",
      "status": "completed",
      "conclusion": "startup_failure",
      "event": "pull_request",
      "created_at": "2026-02-09T08:51:18Z",
      "updated_at": "2026-02-09T08:51:18Z",
      "html_url": "https://github.com/tile-ai/tilelang-ascend/actions/runs/21818352198",
      "durationInSeconds": 0,
      "pull_requests": [],
      "jobs": []
    },
    {
      "id": 21817582213,
      "name": "CI",
      "head_branch": "npuir-exp",
      "head_sha": "318c11c88b56159174f11a29e1087877b05b600d",
      "status": "completed",
      "conclusion": "startup_failure",
      "event": "pull_request",
      "created_at": "2026-02-09T08:24:43Z",
      "updated_at": "2026-02-09T08:24:43Z",
      "html_url": "https://github.com/tile-ai/tilelang-ascend/actions/runs/21817582213",
      "durationInSeconds": 0,
      "pull_requests": [],
      "jobs": []
    },
    {
      "id": 21817405463,
      "name": "CI",
      "head_branch": "npuir-exp",
      "head_sha": "261600a639407615fab6077f76bb5e19a592ff27",
      "status": "completed",
      "conclusion": "startup_failure",
      "event": "pull_request",
      "created_at": "2026-02-09T08:18:37Z",
      "updated_at": "2026-02-09T08:18:37Z",
      "html_url": "https://github.com/tile-ai/tilelang-ascend/actions/runs/21817405463",
      "durationInSeconds": 0,
      "pull_requests": [],
      "jobs": []
    },
    {
      "id": 21816921934,
      "name": "CI",
      "head_branch": "npuir-exp",
      "head_sha": "67dc291f9b97a04a6cd9fe9880517ac2df4feadd",
      "status": "completed",
      "conclusion": "startup_failure",
      "event": "pull_request",
      "created_at": "2026-02-09T08:00:14Z",
      "updated_at": "2026-02-09T08:00:14Z",
      "html_url": "https://github.com/tile-ai/tilelang-ascend/actions/runs/21816921934",
      "durationInSeconds": 0,
      "pull_requests": [],
      "jobs": []
    },
    {
      "id": 21816669895,
      "name": "documentation",
      "head_branch": "ascendc_pto",
      "head_sha": "561466d89244ff4fe16cf6822dde5a8a0c2587a9",
      "status": "completed",
      "conclusion": "startup_failure",
      "event": "pull_request_target",
      "created_at": "2026-02-09T07:50:24Z",
      "updated_at": "2026-02-09T07:50:24Z",
      "html_url": "https://github.com/tile-ai/tilelang-ascend/actions/runs/21816669895",
      "durationInSeconds": 0,
      "pull_requests": [],
      "jobs": []
    },
    {
      "id": 21816577692,
      "name": "CI",
      "head_branch": "ascendc_pto",
      "head_sha": "561466d89244ff4fe16cf6822dde5a8a0c2587a9",
      "status": "completed",
      "conclusion": "startup_failure",
      "event": "pull_request",
      "created_at": "2026-02-09T07:46:13Z",
      "updated_at": "2026-02-09T07:46:13Z",
      "html_url": "https://github.com/tile-ai/tilelang-ascend/actions/runs/21816577692",
      "durationInSeconds": 0,
      "pull_requests": [],
      "jobs": []
    },
    {
      "id": 21816362255,
      "name": "CI",
      "head_branch": "npuir-exp",
      "head_sha": "544a4fda4ed62fabf7b2757ce3793eed0cf252d6",
      "status": "completed",
      "conclusion": "startup_failure",
      "event": "pull_request",
      "created_at": "2026-02-09T07:37:42Z",
      "updated_at": "2026-02-09T07:37:42Z",
      "html_url": "https://github.com/tile-ai/tilelang-ascend/actions/runs/21816362255",
      "durationInSeconds": 0,
      "pull_requests": [],
      "jobs": []
    },
    {
      "id": 21816361262,
      "name": "Reminder Bot",
      "head_branch": "npuir-exp",
      "head_sha": "544a4fda4ed62fabf7b2757ce3793eed0cf252d6",
      "status": "completed",
      "conclusion": "startup_failure",
      "event": "pull_request_target",
      "created_at": "2026-02-09T07:37:40Z",
      "updated_at": "2026-02-09T07:37:40Z",
      "html_url": "https://github.com/tile-ai/tilelang-ascend/actions/runs/21816361262",
      "durationInSeconds": 0,
      "pull_requests": [],
      "jobs": []
    },
    {
      "id": 21816237401,
      "name": "CI",
      "head_branch": "ascendc_pto",
      "head_sha": "b067e262075d4b738de41a0c56b9e53ad32de031",
      "status": "completed",
      "conclusion": "startup_failure",
      "event": "pull_request",
      "created_at": "2026-02-09T07:32:42Z",
      "updated_at": "2026-02-09T07:32:42Z",
      "html_url": "https://github.com/tile-ai/tilelang-ascend/actions/runs/21816237401",
      "durationInSeconds": 0,
      "pull_requests": [],
      "jobs": []
    },
    {
      "id": 21816237460,
      "name": "CI",
      "head_branch": "ascendc_pto",
      "head_sha": "b067e262075d4b738de41a0c56b9e53ad32de031",
      "status": "completed",
      "conclusion": "startup_failure",
      "event": "pull_request",
      "created_at": "2026-02-09T07:32:42Z",
      "updated_at": "2026-02-09T07:32:42Z",
      "html_url": "https://github.com/tile-ai/tilelang-ascend/actions/runs/21816237460",
      "durationInSeconds": 0,
      "pull_requests": [],
      "jobs": []
    },
    {
      "id": 21816229057,
      "name": "documentation",
      "head_branch": "ascendc_pto",
      "head_sha": "3ee959cc5dddbabf0b9f318cdbe7f17dc54231d4",
      "status": "completed",
      "conclusion": "startup_failure",
      "event": "pull_request_target",
      "created_at": "2026-02-09T07:32:21Z",
      "updated_at": "2026-02-09T07:32:21Z",
      "html_url": "https://github.com/tile-ai/tilelang-ascend/actions/runs/21816229057",
      "durationInSeconds": 0,
      "pull_requests": [],
      "jobs": []
    },
    {
      "id": 21815130634,
      "name": "documentation",
      "head_branch": "ascendc_pto",
      "head_sha": "77072381834f81976e13f84d1e36e6b29b8f34e6",
      "status": "completed",
      "conclusion": "startup_failure",
      "event": "pull_request_target",
      "created_at": "2026-02-09T06:45:01Z",
      "updated_at": "2026-02-09T06:45:01Z",
      "html_url": "https://github.com/tile-ai/tilelang-ascend/actions/runs/21815130634",
      "durationInSeconds": 0,
      "pull_requests": [],
      "jobs": []
    },
    {
      "id": 21814725171,
      "name": "CI",
      "head_branch": "ascendc_pto",
      "head_sha": "3ee959cc5dddbabf0b9f318cdbe7f17dc54231d4",
      "status": "completed",
      "conclusion": "startup_failure",
      "event": "pull_request",
      "created_at": "2026-02-09T06:27:14Z",
      "updated_at": "2026-02-09T06:27:14Z",
      "html_url": "https://github.com/tile-ai/tilelang-ascend/actions/runs/21814725171",
      "durationInSeconds": 0,
      "pull_requests": [],
      "jobs": []
    },
    {
      "id": 21814476279,
      "name": "documentation",
      "head_branch": "sk",
      "head_sha": "bb0f65b9ba3281ee727604ecd51a4fe4e66b681c",
      "status": "completed",
      "conclusion": "startup_failure",
      "event": "pull_request_target",
      "created_at": "2026-02-09T06:15:58Z",
      "updated_at": "2026-02-09T06:15:58Z",
      "html_url": "https://github.com/tile-ai/tilelang-ascend/actions/runs/21814476279",
      "durationInSeconds": 0,
      "pull_requests": [],
      "jobs": []
    },
    {
      "id": 21811482231,
      "name": "CI",
      "head_branch": "ascendc_pto",
      "head_sha": "c0b4571963055ba889d7e8bb8f5daf579ecda80e",
      "status": "completed",
      "conclusion": "startup_failure",
      "event": "pull_request",
      "created_at": "2026-02-09T03:37:44Z",
      "updated_at": "2026-02-09T03:37:44Z",
      "html_url": "https://github.com/tile-ai/tilelang-ascend/actions/runs/21811482231",
      "durationInSeconds": 0,
      "pull_requests": [],
      "jobs": []
    },
    {
      "id": 21811337311,
      "name": "CI",
      "head_branch": "ascendc_pto",
      "head_sha": "9bb527b431c93cfb3d2354fdc7bf054e32bc8b06",
      "status": "completed",
      "conclusion": "startup_failure",
      "event": "pull_request",
      "created_at": "2026-02-09T03:28:55Z",
      "updated_at": "2026-02-09T03:28:55Z",
      "html_url": "https://github.com/tile-ai/tilelang-ascend/actions/runs/21811337311",
      "durationInSeconds": 0,
      "pull_requests": [],
      "jobs": []
    },
    {
      "id": 21811337044,
      "name": "Reminder Bot",
      "head_branch": "ascendc_pto",
      "head_sha": "9bb527b431c93cfb3d2354fdc7bf054e32bc8b06",
      "status": "completed",
      "conclusion": "startup_failure",
      "event": "pull_request_target",
      "created_at": "2026-02-09T03:28:54Z",
      "updated_at": "2026-02-09T03:28:54Z",
      "html_url": "https://github.com/tile-ai/tilelang-ascend/actions/runs/21811337044",
      "durationInSeconds": 0,
      "pull_requests": [],
      "jobs": []
    },
    {
      "id": 21810742606,
      "name": "documentation",
      "head_branch": "npuir_brc",
      "head_sha": "4d29d26c1d37d7e95b05259b467bf00213f5507d",
      "status": "completed",
      "conclusion": "startup_failure",
      "event": "pull_request_target",
      "created_at": "2026-02-09T02:54:57Z",
      "updated_at": "2026-02-09T02:54:57Z",
      "html_url": "https://github.com/tile-ai/tilelang-ascend/actions/runs/21810742606",
      "durationInSeconds": 0,
      "pull_requests": [],
      "jobs": []
    },
    {
      "id": 21810677527,
      "name": "documentation",
      "head_branch": "clear",
      "head_sha": "a870e74e591875da278e622414c5eb85f60d8e54",
      "status": "completed",
      "conclusion": "startup_failure",
      "event": "pull_request_target",
      "created_at": "2026-02-09T02:51:07Z",
      "updated_at": "2026-02-09T02:51:07Z",
      "html_url": "https://github.com/tile-ai/tilelang-ascend/actions/runs/21810677527",
      "durationInSeconds": 0,
      "pull_requests": [],
      "jobs": []
    },
    {
      "id": 21810647873,
      "name": "CI",
      "head_branch": "clear",
      "head_sha": "a870e74e591875da278e622414c5eb85f60d8e54",
      "status": "completed",
      "conclusion": "startup_failure",
      "event": "pull_request",
      "created_at": "2026-02-09T02:49:20Z",
      "updated_at": "2026-02-09T02:49:20Z",
      "html_url": "https://github.com/tile-ai/tilelang-ascend/actions/runs/21810647873",
      "durationInSeconds": 0,
      "pull_requests": [],
      "jobs": []
    },
    {
      "id": 21810647624,
      "name": "Reminder Bot",
      "head_branch": "clear",
      "head_sha": "a870e74e591875da278e622414c5eb85f60d8e54",
      "status": "completed",
      "conclusion": "startup_failure",
      "event": "pull_request_target",
      "created_at": "2026-02-09T02:49:19Z",
      "updated_at": "2026-02-09T02:49:19Z",
      "html_url": "https://github.com/tile-ai/tilelang-ascend/actions/runs/21810647624",
      "durationInSeconds": 0,
      "pull_requests": [],
      "jobs": []
    },
    {
      "id": 21809505320,
      "name": "CI",
      "head_branch": "sk",
      "head_sha": "bb0f65b9ba3281ee727604ecd51a4fe4e66b681c",
      "status": "completed",
      "conclusion": "startup_failure",
      "event": "pull_request",
      "created_at": "2026-02-09T01:43:10Z",
      "updated_at": "2026-02-09T01:43:10Z",
      "html_url": "https://github.com/tile-ai/tilelang-ascend/actions/runs/21809505320",
      "durationInSeconds": 0,
      "pull_requests": [],
      "jobs": []
    },
    {
      "id": 21809504922,
      "name": "Reminder Bot",
      "head_branch": "sk",
      "head_sha": "bb0f65b9ba3281ee727604ecd51a4fe4e66b681c",
      "status": "completed",
      "conclusion": "startup_failure",
      "event": "pull_request_target",
      "created_at": "2026-02-09T01:43:09Z",
      "updated_at": "2026-02-09T01:43:09Z",
      "html_url": "https://github.com/tile-ai/tilelang-ascend/actions/runs/21809504922",
      "durationInSeconds": 0,
      "pull_requests": [],
      "jobs": []
    }
  ]
}