{
  "date": "2026-02-25",
  "repo": "tile-ai/tilelang-ascend",
  "runs": [
    {
      "id": 22395712417,
      "name": "documentation",
      "head_branch": "ascendc_pto",
      "head_sha": "6f440b1bffb582b494678b5d7446866fb30830ca",
      "status": "completed",
      "conclusion": "startup_failure",
      "event": "pull_request_target",
      "created_at": "2026-02-25T11:54:28Z",
      "updated_at": "2026-02-25T11:54:28Z",
      "html_url": "https://github.com/tile-ai/tilelang-ascend/actions/runs/22395712417",
      "durationInSeconds": 0,
      "pull_requests": [],
      "jobs": []
    },
    {
      "id": 22388418965,
      "name": "CI",
      "head_branch": "jit-npu",
      "head_sha": "4d2d4e774b88302d3e5022ce684721dab511b416",
      "status": "completed",
      "conclusion": "startup_failure",
      "event": "pull_request",
      "created_at": "2026-02-25T08:23:18Z",
      "updated_at": "2026-02-25T08:23:18Z",
      "html_url": "https://github.com/tile-ai/tilelang-ascend/actions/runs/22388418965",
      "durationInSeconds": 0,
      "pull_requests": [],
      "jobs": []
    },
    {
      "id": 22385907926,
      "name": "Bot",
      "head_branch": "ascendc_pto",
      "head_sha": "324e1634c1cf2b57b5f13f0ca5693f92015a0a9a",
      "status": "completed",
      "conclusion": "startup_failure",
      "event": "issue_comment",
      "created_at": "2026-02-25T06:58:40Z",
      "updated_at": "2026-02-25T06:58:40Z",
      "html_url": "https://github.com/tile-ai/tilelang-ascend/actions/runs/22385907926",
      "durationInSeconds": 0,
      "pull_requests": [],
      "jobs": []
    },
    {
      "id": 22385366811,
      "name": "CI",
      "head_branch": "cj_feature_vector_core_pipeline",
      "head_sha": "7e6b4eea3e2b382abd08814aa8330211dcb261e9",
      "status": "completed",
      "conclusion": "startup_failure",
      "event": "pull_request",
      "created_at": "2026-02-25T06:38:04Z",
      "updated_at": "2026-02-25T06:38:04Z",
      "html_url": "https://github.com/tile-ai/tilelang-ascend/actions/runs/22385366811",
      "durationInSeconds": 0,
      "pull_requests": [],
      "jobs": []
    },
    {
      "id": 22385366576,
      "name": "Reminder Bot",
      "head_branch": "cj_feature_vector_core_pipeline",
      "head_sha": "7e6b4eea3e2b382abd08814aa8330211dcb261e9",
      "status": "completed",
      "conclusion": "startup_failure",
      "event": "pull_request_target",
      "created_at": "2026-02-25T06:38:04Z",
      "updated_at": "2026-02-25T06:38:04Z",
      "html_url": "https://github.com/tile-ai/tilelang-ascend/actions/runs/22385366576",
      "durationInSeconds": 0,
      "pull_requests": [],
      "jobs": []
    },
    {
      "id": 22380878229,
      "name": "CI",
      "head_branch": "ascendc_pto",
      "head_sha": "9081f42d6db54de90481e20fd58aab8b495f9b88",
      "status": "completed",
      "conclusion": "startup_failure",
      "event": "pull_request",
      "created_at": "2026-02-25T03:29:06Z",
      "updated_at": "2026-02-25T03:29:06Z",
      "html_url": "https://github.com/tile-ai/tilelang-ascend/actions/runs/22380878229",
      "durationInSeconds": 0,
      "pull_requests": [],
      "jobs": []
    },
    {
      "id": 22380772186,
      "name": "CI",
      "head_branch": "ascendc_pto",
      "head_sha": "6f440b1bffb582b494678b5d7446866fb30830ca",
      "status": "completed",
      "conclusion": "startup_failure",
      "event": "pull_request",
      "created_at": "2026-02-25T03:24:17Z",
      "updated_at": "2026-02-25T03:24:17Z",
      "html_url": "https://github.com/tile-ai/tilelang-ascend/actions/runs/22380772186",
      "durationInSeconds": 0,
      "pull_requests": [],
      "jobs": []
    },
    {
      "id": 22380771742,
      "name": "Reminder Bot",
      "head_branch": "ascendc_pto",
      "head_sha": "6f440b1bffb582b494678b5d7446866fb30830ca",
      "status": "completed",
      "conclusion": "startup_failure",
      "event": "pull_request_target",
      "created_at": "2026-02-25T03:24:16Z",
      "updated_at": "2026-02-25T03:24:16Z",
      "html_url": "https://github.com/tile-ai/tilelang-ascend/actions/runs/22380771742",
      "durationInSeconds": 0,
      "pull_requests": [],
      "jobs": []
    },
    {
      "id": 22380381048,
      "name": "CI",
      "head_branch": "jit-npu",
      "head_sha": "e6b6d3de605a58c2526f7e6ca5ab73652fe05ee4",
      "status": "completed",
      "conclusion": "startup_failure",
      "event": "pull_request",
      "created_at": "2026-02-25T03:06:51Z",
      "updated_at": "2026-02-25T03:06:51Z",
      "html_url": "https://github.com/tile-ai/tilelang-ascend/actions/runs/22380381048",
      "durationInSeconds": 0,
      "pull_requests": [],
      "jobs": []
    },
    {
      "id": 22380107961,
      "name": "documentation",
      "head_branch": "fix_copy_shape_tests",
      "head_sha": "f6c206abb10d04e9c8f5b1468e111a57c787f6cc",
      "status": "completed",
      "conclusion": "startup_failure",
      "event": "pull_request_target",
      "created_at": "2026-02-25T02:55:34Z",
      "updated_at": "2026-02-25T02:55:34Z",
      "html_url": "https://github.com/tile-ai/tilelang-ascend/actions/runs/22380107961",
      "durationInSeconds": 0,
      "pull_requests": [],
      "jobs": []
    },
    {
      "id": 22380041550,
      "name": "Reminder Bot",
      "head_branch": "fix_copy_shape_tests",
      "head_sha": "f6c206abb10d04e9c8f5b1468e111a57c787f6cc",
      "status": "completed",
      "conclusion": "startup_failure",
      "event": "pull_request_target",
      "created_at": "2026-02-25T02:52:44Z",
      "updated_at": "2026-02-25T02:52:44Z",
      "html_url": "https://github.com/tile-ai/tilelang-ascend/actions/runs/22380041550",
      "durationInSeconds": 0,
      "pull_requests": [],
      "jobs": []
    },
    {
      "id": 22380041816,
      "name": "CI",
      "head_branch": "fix_copy_shape_tests",
      "head_sha": "f6c206abb10d04e9c8f5b1468e111a57c787f6cc",
      "status": "completed",
      "conclusion": "startup_failure",
      "event": "pull_request",
      "created_at": "2026-02-25T02:52:44Z",
      "updated_at": "2026-02-25T02:52:44Z",
      "html_url": "https://github.com/tile-ai/tilelang-ascend/actions/runs/22380041816",
      "durationInSeconds": 0,
      "pull_requests": [],
      "jobs": []
    },
    {
      "id": 22378595669,
      "name": "documentation",
      "head_branch": "dev",
      "head_sha": "60fdcdc38018d68617b81f6648ad2f0b69c5ff38",
      "status": "completed",
      "conclusion": "startup_failure",
      "event": "pull_request_target",
      "created_at": "2026-02-25T01:53:22Z",
      "updated_at": "2026-02-25T01:53:22Z",
      "html_url": "https://github.com/tile-ai/tilelang-ascend/actions/runs/22378595669",
      "durationInSeconds": 0,
      "pull_requests": [],
      "jobs": []
    }
  ]
}